arcade_microsoft/__init__.py
arcade_microsoft/client.py
arcade_microsoft/outlook_calendar/__init__.py
arcade_microsoft/outlook_calendar/_utils.py
arcade_microsoft/outlook_calendar/constants.py
arcade_microsoft/outlook_calendar/models.py
arcade_microsoft/outlook_calendar/tools/__init__.py
arcade_microsoft/outlook_calendar/tools/create_event.py
arcade_microsoft/outlook_calendar/tools/get_event.py
arcade_microsoft/outlook_calendar/tools/list_events_in_time_range.py
arcade_microsoft/outlook_mail/__init__.py
arcade_microsoft/outlook_mail/_utils.py
arcade_microsoft/outlook_mail/constants.py
arcade_microsoft/outlook_mail/enums.py
arcade_microsoft/outlook_mail/message.py
arcade_microsoft/outlook_mail/tools/__init__.py
arcade_microsoft/outlook_mail/tools/read.py
arcade_microsoft/outlook_mail/tools/send.py
arcade_microsoft/outlook_mail/tools/write.py
arcade_microsoft-1.1.1.dist-info/METADATA
arcade_microsoft-1.1.1.dist-info/WHEEL
arcade_microsoft-1.1.1.dist-info/licenses/LICENSE
arcade_microsoft-1.1.1.dist-info/RECORD
